{
  "$schema": "https://turbo.build/schema.json",
  "globalDependencies": ["**/.env.*local"],
  "tasks": {
    "build": {
      "dependsOn": ["^build"],
      "outputs": ["dist/**", ".svelte-kit/**", "build/**"],
      "cache": true
    },
    "dev": {
      "cache": false,
      "persistent": true
    },
    "test": {
      "dependsOn": ["build"],
      "outputs": ["coverage/**"],
      "cache": true
    },
    "test:watch": {
      "cache": false,
      "persistent": true
    },
    "test:coverage": {
      "dependsOn": ["build"],
      "outputs": ["coverage/**"],
      "cache": true
    },
    "lint": {
      "cache": true,
      "outputs": []
    },
    "lint:fix": {
      "cache": false,
      "outputs": []
    },
    "type-check": {
      "dependsOn": ["^build"],
      "cache": true,
      "outputs": []
    },
    "generate:types": {
      "cache": true,
      "outputs": ["src/generated/**"]
    },
    "clean": {
      "cache": false,
      "outputs": []
    },
    "migrate": {
      "cache": false,
      "outputs": []
    },
    "seed": {
      "cache": false,
      "outputs": []
    }
  }
}
